Workbook

Sheet Inputs
A1: Larkspur Tools, Inc.: model inputs
A2: $ in millions unless noted; rates as decimals
A4: Active case | C4: 1 | D4: 1 = Base, 2 = Upside
A6: Scenario drivers | F6: FY2026E | G6: FY2027E | H6: FY2028E | I6: FY2029E | J6: FY2030E
A7: Revenue growth: Base | F7: 0.06 | G7: 0.055 | H7: 0.05 | I7: 0.045 | J7: 0.04
A8: Revenue growth: Upside | F8: 0.08 | G8: 0.075 | H8: 0.07 | I8: 0.06 | J8: 0.05
A10: Revenue growth: active case | F10: =CHOOSE($C$4,F7,F8) | G10: =CHOOSE($C$4,G7,G8) | H10: =CHOOSE($C$4,H7,H8) | I10: =CHOOSE($C$4,I7,I8) | J10: =CHOOSE($C$4,J7,J8)
A12: Gross margin: Base | F12: 0.4 | G12: 0.402 | H12: 0.404 | I12: 0.405 | J12: 0.405
A13: Gross margin: Upside | F13: 0.405 | G13: 0.41 | H13: 0.415 | I13: 0.418 | J13: 0.42
A15: Gross margin: active case | F15: =CHOOSE($C$4,F12,F13) | G15: =CHOOSE($C$4,G12,G13) | H15: =CHOOSE($C$4,H12,H13) | I15: =CHOOSE($C$4,I12,I13) | J15: =CHOOSE($C$4,J12,J13)
A17: Operating drivers | F17: FY2026E | G17: FY2027E | H17: FY2028E | I17: FY2029E | J17: FY2030E
A18: SG&A, % of revenue | F18: 0.175 | G18: 0.175 | H18: 0.175 | I18: 0.175 | J18: 0.175
A19: R&D, % of revenue | F19: 0.07 | G19: 0.07 | H19: 0.07 | I19: 0.07 | J19: 0.07
A20: Stock-based compensation, % of revenue | F20: 0.015 | G20: 0.015 | H20: 0.015 | I20: 0.015 | J20: 0.015
A21: D&A, % of revenue | F21: 0.04 | G21: 0.04 | H21: 0.04 | I21: 0.04 | J21: 0.04
A22: Capital expenditures, % of revenue | F22: 0.045 | G22: 0.045 | H22: 0.045 | I22: 0.045 | J22: 0.045
A23: Tax rate | C23: 0.25
A24: Interest rate on beginning-of-year debt | C24: 0.06
A25: Days sales outstanding (on revenue) | C25: 46
A26: Days inventory outstanding (on COGS) | C26: 90
A27: Days payables outstanding (on COGS) | C27: 50
A28: Mandatory debt repayment | F28: 20 | G28: 20 | H28: 20 | I28: 20 | J28: 20
A30: Valuation
A31: WACC | C31: 0.09
A32: Terminal growth rate | C32: 0.025
A33: Diluted shares outstanding (millions) | C33: 52
A34: Valuation date | C34: End of FY2025A

Sheet IS
A1: Larkspur Tools, Inc.: income statement
A2: $ in millions
A3: Fiscal year | C3: FY2023A | D3: FY2024A | E3: FY2025A | F3: FY2026E | G3: FY2027E | H3: FY2028E | I3: FY2029E | J3: FY2030E
A5: Revenue | C5: 812 | D5: 873 | E5: 931 | F5: =E5*(1+Inputs!F10) | G5: =F5*(1+Inputs!G10) | H5: =G5*(1+Inputs!H10) | I5: =H5*(1+Inputs!I10) | J5: =I5*(1+Inputs!J10)
A6: Revenue growth | D6: =D5/C5-1 | E6: =E5/D5-1 | F6: =F5/E5-1 | G6: =G5/F5-1 | H6: =H5/G5-1 | I6: =I5/H5-1 | J6: =J5/I5-1
A7: Cost of goods sold | C7: 495.3 | D7: 528.2 | E7: 558.6 | F7: =F5*(1-Inputs!F15) | G7: =G5*(1-Inputs!G15) | H7: =H5*(1-Inputs!H15) | I7: =I5*(1-Inputs!I15) | J7: =J5*(1-Inputs!J15)
A8: Gross profit | C8: =C5-C7 | D8: =D5-D7 | E8: =E5-E7 | F8: =F5-F7 | G8: =G5-G7 | H8: =H5-H7 | I8: =I5-I7 | J8: =J5-J7
A9: Gross margin | C9: =C8/C5 | D9: =D8/D5 | E9: =E8/E5 | F9: =F8/F5 | G9: =G8/G5 | H9: =H8/H5 | I9: =I8/I5 | J9: =J8/J5
A11: SG&A | C11: 146.2 | D11: 155.4 | E11: 163 | F11: =F5*Inputs!F18 | G11: =G5*Inputs!G18 | H11: =H5*Inputs!H18 | I11: =I5*Inputs!I18 | J11: =J5*Inputs!J18
A12: R&D | C12: 56.8 | D12: 61.1 | E12: 65.2 | F12: =F5*Inputs!F19 | G12: =G5*Inputs!G19 | H12: =H5*Inputs!H19 | I12: =I5*Inputs!I19 | J12: =J5*Inputs!J19
A13: Stock-based compensation | C13: 12.2 | D13: 13.1 | E13: 14 | F13: =F5*Inputs!F20 | G13: =G5*Inputs!G20 | H13: =H5*Inputs!H20 | I13: =I5*Inputs!I20 | J13: =J5*Inputs!J20
A14: Total operating expenses | C14: =SUM(C11:C12) | D14: =SUM(D11:D12) | E14: =SUM(E11:E12) | F14: =SUM(F11:F12) | G14: =SUM(G11:G12) | H14: =SUM(H11:H12) | I14: =SUM(I11:I12) | J14: =SUM(J11:J12)
A15: EBITDA | C15: =C8-C14 | D15: =D8-D14 | E15: =E8-E14 | F15: =F8-F14 | G15: =G8-G14 | H15: =H8-H14 | I15: =I8-I14 | J15: =J8-J14
A16: EBITDA margin | C16: =C15/C5 | D16: =D15/D5 | E16: =E15/E5 | F16: =F15/F5 | G16: =G15/G5 | H16: =H15/H5 | I16: =I15/I5 | J16: =J15/J5
A17: Depreciation and amortization | C17: 32.5 | D17: 34.9 | E17: 37.2 | F17: =F5*Inputs!F21 | G17: =G5*Inputs!G21 | H17: =H5*Inputs!H21 | I17: =I5*Inputs!I21 | J17: =J5*Inputs!J21
A18: EBIT | C18: =C15-C17 | D18: =D15-D17 | E18: =E15-E17 | F18: =F15-F17 | G18: =G15-G17 | H18: =H15-H17 | I18: =I15-I17 | J18: =J15-J17
A19: Interest expense | C19: 18 | D19: 17.2 | E19: 16.4 | F19: =Inputs!$C$24*BS!E16 | G19: =Inputs!$C$24*BS!F16 | H19: =Inputs!$C$24*BS!G16 | I19: =Inputs!$C$24*BS!H16 | J19: =Inputs!$C$24*BS!I16
A20: Pre-tax income | C20: =C18-C19 | D20: =D18-D19 | E20: =E18-E19 | F20: =F18-F19 | G20: =G18-G19 | H20: =H18-H19 | I20: =I18-I19 | J20: =J18-J19
A21: Income tax expense | C21: 12.8 | D21: 15.8 | E21: 19.1 | F21: =F20*Inputs!$C$23 | G21: =G20*Inputs!$C$23 | H21: =H20*Inputs!$C$23 | I21: =I20*Inputs!$C$23 | J21: =J20*Inputs!$C$23
A22: Net income | C22: =C20-C21 | D22: =D20-D21 | E22: =E20-E21 | F22: =F20-F21 | G22: =G20-G21 | H22: =H20-H21 | I22: =I20-I21 | J22: =J20-J21

Sheet BS
A1: Larkspur Tools, Inc.: balance sheet
A2: $ in millions
A3: Fiscal year | C3: FY2023A | D3: FY2024A | E3: FY2025A | F3: FY2026E | G3: FY2027E | H3: FY2028E | I3: FY2029E | J3: FY2030E
A4: Assets
A5: Cash | C5: 50.5 | D5: 77.6 | E5: 116.6 | F5: =CF!F22 | G5: =CF!G22 | H5: =CF!H22 | I5: =CF!I22 | J5: =CF!J22
A6: Accounts receivable | C6: 101.9 | D6: 109.5 | E6: 117 | F6: =IS!F5*Inputs!$C$25/365 | G6: =IS!G5*Inputs!$C$25/365 | H6: =IS!H5*Inputs!$C$25/365 | I6: =IS!I5*Inputs!$C$25/365 | J6: =IS!J5*Inputs!$C$25/365
A7: Inventory | C7: 124.5 | D7: 131.3 | E7: 137.7 | F7: =IS!F7*Inputs!$C$26/365 | G7: =IS!G7*Inputs!$C$26/365 | H7: =IS!H7*Inputs!$C$26/365 | I7: =IS!I7*Inputs!$C$26/365 | J7: =IS!J7*Inputs!$C$26/365
A8: Total current assets | C8: =SUM(C5:C7) | D8: =SUM(D5:D7) | E8: =SUM(E5:E7) | F8: =SUM(F5:F7) | G8: =SUM(G5:G7) | H8: =SUM(H5:H7) | I8: =SUM(I5:I7) | J8: =SUM(J5:J7)
A9: PP&E, net | C9: 291.4 | D9: 296 | E9: 300 | F9: =E9-CF!F14-IS!F17 | G9: =F9-CF!G14-IS!G17 | H9: =G9-CF!H14-IS!H17 | I9: =H9-CF!I14-IS!I17 | J9: =I9-CF!J14-IS!J17
A10: Goodwill | C10: 150 | D10: 150 | E10: 150 | F10: =E10 | G10: =F10 | H10: =G10 | I10: =H10 | J10: =I10
A11: Total assets | C11: =C8+C9+C10 | D11: =D8+D9+D10 | E11: =E8+E9+E10 | F11: =F8+F9+F10 | G11: =G8+G9+G10 | H11: =H8+H9+H10 | I11: =I8+I9+I10 | J11: =J8+J9+J10
A12: Liabilities and equity
A13: Accounts payable | C13: 69.4 | D13: 73.1 | E13: 76.5 | F13: =IS!F7*Inputs!$C$27/365 | G13: =IS!G7*Inputs!$C$27/365 | H13: =IS!H7*Inputs!$C$27/365 | I13: =IS!I7*Inputs!$C$27/365 | J13: =IS!J7*Inputs!$C$27/365
A14: Accrued expenses | C14: 36 | D14: 38 | E14: 40 | F14: =E14 | G14: =F14 | H14: =G14 | I14: =H14 | J14: =I14
A15: Total current liabilities | C15: =SUM(C13:C14) | D15: =SUM(D13:D14) | E15: =SUM(E13:E14) | F15: =SUM(F13:F14) | G15: =SUM(G13:G14) | H15: =SUM(H13:H14) | I15: =SUM(I13:I14) | J15: =SUM(J13:J14)
A16: Long-term debt | C16: 300 | D16: 280 | E16: 260 | F16: =E16+CF!F17 | G16: =F16+CF!G17 | H16: =G16+CF!H17 | I16: =H16+CF!I17 | J16: =I16+CF!J17
A17: Total liabilities | C17: =C15+C16 | D17: =D15+D16 | E17: =E15+E16 | F17: =F15+F16 | G17: =G15+G16 | H17: =H15+H16 | I17: =I15+I16 | J17: =J15+J16
A18: Common stock and APIC | C18: 152.9 | D18: 166 | E18: 180 | F18: =E18+IS!F13 | G18: =F18+IS!G13 | H18: =G18+IS!H13 | I18: =H18+IS!I13 | J18: =I18+IS!J13
A19: Retained earnings | C19: 160 | D19: 207.3 | E19: 264.8 | F19: =E19+IS!F22 | G19: =F19+IS!G22 | H19: =G19+IS!H22 | I19: =H19+IS!I22 | J19: =I19+IS!J22
A20: Total equity | C20: =C18+C19 | D20: =D18+D19 | E20: =E18+E19 | F20: =F18+F19 | G20: =G18+G19 | H20: =H18+H19 | I20: =I18+I19 | J20: =J18+J19
A21: Total liabilities and equity | C21: =C17+C20 | D21: =D17+D20 | E21: =E17+E20 | F21: =F17+F20 | G21: =G17+G20 | H21: =H17+H20 | I21: =I17+I20 | J21: =J17+J20
A23: Check: assets - liabilities - equity (should be 0) | C23: =C11-C21 | D23: =D11-D21 | E23: =E11-E21 | F23: =F11-F21 | G23: =G11-G21 | H23: =H11-H21 | I23: =I11-I21 | J23: =J11-J21

Sheet CF
A1: Larkspur Tools, Inc.: cash flow statement (forecast years)
A2: $ in millions
A3: Fiscal year | F3: FY2026E | G3: FY2027E | H3: FY2028E | I3: FY2029E | J3: FY2030E
A5: Net income | F5: =IS!F22 | G5: =IS!G22 | H5: =IS!H22 | I5: =IS!I22 | J5: =IS!J22
A6: Depreciation and amortization | F6: =IS!F17 | G6: =IS!G17 | H6: =IS!H17 | I6: =IS!I17 | J6: =IS!J17
A7: Stock-based compensation | F7: =IS!F13 | G7: =IS!G13 | H7: =IS!H13 | I7: =IS!I13 | J7: =IS!J13
A8: (Increase) / decrease in receivables | F8: =BS!E6-BS!F6 | G8: =BS!F6-BS!G6 | H8: =BS!G6-BS!H6 | I8: =BS!H6-BS!I6 | J8: =BS!I6-BS!J6
A9: (Increase) / decrease in inventory | F9: =BS!E7-BS!F7 | G9: =BS!F7-BS!G7 | H9: =BS!G7-BS!H7 | I9: =BS!H7-BS!I7 | J9: =BS!I7-BS!J7
A10: Increase / (decrease) in payables | F10: =BS!F13-BS!E13 | G10: =BS!G13-BS!F13 | H10: =BS!H13-BS!G13 | I10: =BS!I13-BS!H13 | J10: =BS!J13-BS!I13
A11: Increase / (decrease) in accrued expenses | F11: =BS!F14-BS!E14 | G11: =BS!G14-BS!F14 | H11: =BS!H14-BS!G14 | I11: =BS!I14-BS!H14 | J11: =BS!J14-BS!I14
A12: Cash from operating activities | F12: =SUM(F5:F11) | G12: =SUM(G5:G11) | H12: =SUM(H5:H11) | I12: =SUM(I5:I11) | J12: =SUM(J5:J11)
A14: Capital expenditures | F14: =-IS!F5*Inputs!F22 | G14: =-IS!G5*Inputs!G22 | H14: =-IS!H5*Inputs!H22 | I14: =-IS!I5*Inputs!I22 | J14: =-IS!J5*Inputs!J22
A15: Cash from investing activities | F15: =F14 | G15: =G14 | H15: =H14 | I15: =I14 | J15: =J14
A17: Debt repayment | F17: =-MIN(Inputs!F28,BS!E16) | G17: =-MIN(Inputs!G28,BS!F16) | H17: =-MIN(Inputs!H28,BS!G16) | I17: =-MIN(Inputs!I28,BS!H16) | J17: =-MIN(Inputs!J28,BS!I16)
A18: Cash from financing activities | F18: =F17 | G18: =G17 | H18: =H17 | I18: =I17 | J18: =J17
A20: Net change in cash | F20: =F12+F15+F18 | G20: =G12+G15+G18 | H20: =H12+H15+H18 | I20: =I12+I15+I18 | J20: =J12+J15+J18
A21: Beginning cash | F21: =BS!E5 | G21: =BS!F5 | H21: =BS!G5 | I21: =BS!H5 | J21: =BS!I5
A22: Ending cash | F22: =F21+F20 | G22: =G21+G20 | H22: =H21+H20 | I22: =I21+I20 | J22: =J21+J20

Sheet DCF
A1: Larkspur Tools, Inc.: unlevered DCF (valuation date: end of FY2025A)
A2: $ in millions
A3: Fiscal year | F3: FY2026E | G3: FY2027E | H3: FY2028E | I3: FY2029E | J3: FY2030E
A5: EBIT | F5: =IS!F18 | G5: =IS!G18 | H5: =IS!H18 | I5: =IS!I18 | J5: =IS!J18
A6: Tax on EBIT | F6: =-F5*Inputs!$C$23 | G6: =-G5*Inputs!$C$23 | H6: =-H5*Inputs!$C$23 | I6: =-I5*Inputs!$C$23 | J6: =-J5*Inputs!$C$23
A7: NOPAT | F7: =F5+F6 | G7: =G5+G6 | H7: =H5+H6 | I7: =I5+I6 | J7: =J5+J6
A8: Depreciation and amortization | F8: =IS!F17 | G8: =IS!G17 | H8: =IS!H17 | I8: =IS!I17 | J8: =IS!J17
A9: Capital expenditures | F9: =CF!F14 | G9: =CF!G14 | H9: =CF!H14 | I9: =CF!I14 | J9: =CF!J14
A10: Change in net working capital | F10: =SUM(CF!F8:F11) | G10: =SUM(CF!G8:G11) | H10: =SUM(CF!H8:H11) | I10: =SUM(CF!I8:I11) | J10: =SUM(CF!J8:J11)
A11: Unlevered free cash flow | F11: =F7+F8+F9+F10 | G11: =G7+G8+G9+G10 | H11: =H7+H8+H9+H10 | I11: =I7+I8+I9+I10 | J11: =J7+J8+J9+J10
A13: Discount period (years from valuation date) | F13: 1 | G13: =F13+1 | H13: =G13+1 | I13: =H13+1 | J13: =I13+1
A14: Discount factor | F14: =1/(1+Inputs!$C$31)^F13 | G14: =1/(1+Inputs!$C$31)^G13 | H14: =1/(1+Inputs!$C$31)^H13 | I14: =1/(1+Inputs!$C$31)^I13 | J14: =1/(1+Inputs!$C$31)^J13
A15: PV of unlevered free cash flow | F15: =F11*F14 | G15: =G11*G14 | H15: =H11*H14 | I15: =I11*I14 | J15: =J11*J14
A17: Sum of PV of unlevered free cash flow | C17: =SUM(F15:J15)
A18: Terminal value at end of FY2030E (Gordon growth) | C18: =J11*(1+Inputs!$C$32)/(Inputs!$C$31-Inputs!$C$32)
A19: PV of terminal value | C19: =C18*J14
A20: Enterprise value | C20: =C17+C19
A21: Net debt at valuation date | C21: =BS!E16-BS!E5
A22: Equity value | C22: =C20-C21
A23: Diluted shares (millions) | C23: =Inputs!$C$33
A24: Equity value per share ($) | C24: =C22/C23
A25: Terminal value, % of enterprise value | C25: =C19/C20
